{
    "resourceType": "devcenters/galleries/images/versions",
    "apiVersion": "2024-05-01-preview",
    "learnMore": {
        "url": "https://docs.microsoft.com/cli/azure/devcenter/admin/image-version"
    },
    "commands": [
        {
            "name": "az devcenter admin image-version show",
            "description": "Get an image version.",
            "path": "/subscriptions/{subscriptionId}/resourceGroups/{resourceGroupName}/providers/Microsoft.DevCenter/devcenters/{devCenterName}/galleries/{galleryName}/images/{imageName}/versions/{versionName}",
            "confirmation": false,
            "help": {
                "learnMore": {
                    "url": "https://docs.microsoft.com/cli/azure/devcenter/admin/image-version#az-devcenter-admin-image-version-show"
                },
                "parameterSets": [
                    {
                        "parameters": [
                            "[--dev-center]",
                            "[--dev-center-name]",
                            "[--gallery-name]",
                            "[--image-name]",
                            "[--resource-group]",
                            "[--subscription]",
                            "[--name]",
                            "[--version-name]"
                        ]
                    }
                ]
            },
            "examples": [
                {
                    "description": "Get",
                    "parameters": [
                        {
                            "name": "--dev-center",
                            "value": "[path.devCenterName]"
                        },
                        {
                            "name": "--gallery-name",
                            "value": "[path.galleryName]"
                        },
                        {
                            "name": "--image-name",
                            "value": "[path.imageName]"
                        },
                        {
                            "name": "--resource-group",
                            "value": "[path.resourceGroupName]"
                        },
                        {
                            "name": "--name",
                            "value": "[path.versionName]"
                        },
                        {
                            "name": "--subscription",
                            "value": "[path.subscriptionId]"
                        }
                    ]
                }
            ]
        }
    ]
}