{
    "resourceType": "namespaces/wcfRelays/authorizationRules",
    "apiVersion": "2017-04-01",
    "learnMore": {
        "url": "https://docs.microsoft.com/cli/azure/relay/wcfrelay/authorization-rule"
    },
    "commands": [
        {
            "name": "az relay wcfrelay authorization-rule delete",
            "description": "Delete the Authorization Rule of Relay Service WCF Relay.",
            "path": "/subscriptions/{subscriptionId}/resourceGroups/{resourceGroupName}/providers/Microsoft.Relay/namespaces/{namespaceName}/wcfRelays/{relayName}/authorizationRules/{authorizationRuleName}",
            "confirmation": false,
            "help": {
                "learnMore": {
                    "url": "https://docs.microsoft.com/cli/azure/relay/wcfrelay/authorization-rule#az-relay-wcfrelay-authorization-rule-delete"
                },
                "parameterSets": [
                    {
                        "parameters": [
                            "[--name]",
                            "[--namespace-name]",
                            "[--relay-name]",
                            "[--resource-group]",
                            "[--subscription]"
                        ]
                    }
                ]
            },
            "examples": [
                {
                    "description": "Delete the Authorization Rule of Relay Service WCF Relay.",
                    "parameters": [
                        {
                            "name": "--name",
                            "value": "[path.authorizationRuleName]"
                        },
                        {
                            "name": "--namespace-name",
                            "value": "[path.namespaceName]"
                        },
                        {
                            "name": "--relay-name",
                            "value": "[path.relayName]"
                        },
                        {
                            "name": "--resource-group",
                            "value": "[path.resourceGroupName]"
                        },
                        {
                            "name": "--subscription",
                            "value": "[path.subscriptionId]"
                        }
                    ]
                }
            ]
        },
        {
            "name": "az relay wcfrelay authorization-rule show",
            "description": "Show properties of Authorization Rule for the given Relay Service WCF Relay.",
            "path": "/subscriptions/{subscriptionId}/resourceGroups/{resourceGroupName}/providers/Microsoft.Relay/namespaces/{namespaceName}/wcfRelays/{relayName}/authorizationRules/{authorizationRuleName}",
            "confirmation": false,
            "help": {
                "learnMore": {
                    "url": "https://docs.microsoft.com/cli/azure/relay/wcfrelay/authorization-rule#az-relay-wcfrelay-authorization-rule-show"
                },
                "parameterSets": [
                    {
                        "parameters": [
                            "[--name]",
                            "[--namespace-name]",
                            "[--relay-name]",
                            "[--resource-group]",
                            "[--subscription]"
                        ]
                    }
                ]
            },
            "examples": [
                {
                    "description": "show properties of Authorization Rule",
                    "parameters": [
                        {
                            "name": "--resource-group",
                            "value": "[path.resourceGroupName]"
                        },
                        {
                            "name": "--namespace-name",
                            "value": "[path.namespaceName]"
                        },
                        {
                            "name": "--relay-name",
                            "value": "[path.relayName]"
                        },
                        {
                            "name": "--name",
                            "value": "[path.authorizationRuleName]"
                        },
                        {
                            "name": "--subscription",
                            "value": "[path.subscriptionId]"
                        }
                    ]
                }
            ]
        },
        {
            "name": "az relay wcfrelay authorization-rule keys list",
            "description": "List the keys and connection strings of Authorization Rule for the given Relay Service WCF Relay.",
            "path": "/subscriptions/{subscriptionId}/resourceGroups/{resourceGroupName}/providers/Microsoft.Relay/namespaces/{namespaceName}/wcfRelays/{relayName}/authorizationRules/{authorizationRuleName}/listKeys",
            "confirmation": false,
            "help": {
                "learnMore": {
                    "url": "https://docs.microsoft.com/cli/azure/relay/wcfrelay/authorization-rule/keys#az-relay-wcfrelay-authorization-rule-keys-list"
                },
                "parameterSets": [
                    {
                        "parameters": [
                            "[--name]",
                            "[--namespace-name]",
                            "[--relay-name]",
                            "[--resource-group]",
                            "[--subscription]"
                        ]
                    }
                ]
            },
            "examples": [
                {
                    "description": "List the keys and connection strings of Authorization Rule for the given Relay Service WCF Relay.",
                    "parameters": [
                        {
                            "name": "--name",
                            "value": "[path.authorizationRuleName]"
                        },
                        {
                            "name": "--namespace-name",
                            "value": "[path.namespaceName]"
                        },
                        {
                            "name": "--relay-name",
                            "value": "[path.relayName]"
                        },
                        {
                            "name": "--resource-group",
                            "value": "[path.resourceGroupName]"
                        },
                        {
                            "name": "--subscription",
                            "value": "[path.subscriptionId]"
                        }
                    ]
                }
            ]
        }
    ]
}